Metadata-Version: 2.1
Name: geniusmlapi
Version: 0.0.1
Summary: Pacote PyPI para Genius
Home-page: https://github.com/fagnercandido/GeniusMLAPI
Author: Fagner Candido
Author-email: fsouzacandido@gmail.com
License: MIT License
Keywords: Pacote
Platform: UNKNOWN
